bept/__init__.py
bept/main.py
bept/validator.py
bept/analysis/__init__.py
bept/analysis/bept_csv_make.py
bept/analysis/coord_conv.py
bept/analysis/elec_calc.py
bept/analysis/pot_extract.py
bept/analysis/pot_val.py
bept/analysis/pqr_utils.py
bept/analysis/opt_files/__init__.py
bept/analysis/opt_files/cube.py
bept/analysis/opt_files/surface_pdb_sasa.py
bept/analysis/opt_files/xyz.py
bept/auto/__init__.py
bept/auto/auto_execute.py
bept/auto/auto_file.py
bept/docs/auto.md
bept/docs/docs_viewer.py
bept/docs/gen.md
bept/docs/history.md
bept/docs/installation.md
bept/docs/intro.md
bept/docs/out.md
bept/docs/pymol.md
bept/gen/__init__.py
bept/gen/app_runner.py
bept/gen/interface.py
bept/gen/pdb2pqr_beaupy.py
bept/gen/pdb2pqr_textual.py
bept/gen/toml_in_converter.py
bept/history/__init__.py
bept/history/cache_apbs.py
bept/history/cache_vnr.py
bept/history/his_main.py
bept/history/his_utils.py
bept/history/history_apbs.txt
bept/history/history_pdb2pqr.txt
bept/pymol/__init__.py
bept/pymol/mol_ext.py
bept/pymol/pymol_templates/__init__.py
bept/pymol/pymol_templates/aligning_two_proteins.py
bept/pymol/pymol_templates/bulk_mutagenesis.py
bept/pymol/pymol_templates/calc_sasa.py
bept/pymol/pymol_templates/cartoon_representation.py
bept/pymol/pymol_templates/create_color_surface.py
bept/pymol/pymol_templates/dist_bw_atoms.py
bept/pymol/pymol_templates/morphing_two_proteins.py
bept/pymol/pymol_templates/point_mutagenesis.py
bept/pymol/pymol_templates/radius_selection.py
bept/pymol/pymol_templates/show_bumps.py
bept/pymol/pymol_templates/superimpose_two_proteins.py
bept-0.1.0.dist-info/METADATA
bept-0.1.0.dist-info/WHEEL
bept-0.1.0.dist-info/entry_points.txt
bept-0.1.0.dist-info/licenses/LICENSE
bept-0.1.0.dist-info/RECORD
