Metadata-Version: 2.3
Name: bept
Version: 0.1.0
Summary: BEPT is a Beginner friendly Electrostatics for Protein analysis Tool, a cross-platform interactive and user-friendly tool for protein electrostatics using APBS and PDB2PQR.
Project-URL: homepage, https://github.com/IISc-Software-iGEM/bept
Project-URL: documentation, https://github.com/IISc-Software-iGEM/bept/tree/main/docs
Project-URL: repository, https://github.com/IISc-Software-iGEM/bept.git
Author: Anirudh Gupta, Akshita Sunsugu Panliswami, Aditya Thakkar, Kishan Gowda, G Hasini, Soham Paul, Aditey Nandan, Ritabrata Saha, Shreyan Priyadarshi, Deeptam Bhar
Maintainer: Anirudh Gupta
License: MIT License
License-File: LICENSE
Keywords: apbs,bept,cli,cube,dx2cube,electrostatics,pdb2pqr,protein
Classifier: Development Status :: 4 - Beta
Classifier: Intended Audience :: Developers
Classifier: Intended Audience :: Education
Classifier: Intended Audience :: Science/Research
Classifier: License :: OSI Approved :: MIT License
Classifier: Operating System :: MacOS
Classifier: Operating System :: Microsoft :: Windows
Classifier: Operating System :: POSIX
Classifier: Programming Language :: Python :: 3.11
Classifier: Programming Language :: Python :: 3.12
Classifier: Topic :: Education
Classifier: Topic :: Scientific/Engineering :: Bio-Informatics
Requires-Python: >=3.11
Requires-Dist: beaupy
Requires-Dist: biopython>=1.84
Requires-Dist: click>=8.1.7
Requires-Dist: fzf-bin>=0.55.0
Requires-Dist: pandas>=2.2.2
Requires-Dist: pdb2pqr>=3.6.2
Requires-Dist: rich-click>=1.8.3
Requires-Dist: rich>=13.8.0
Requires-Dist: tabulate>=0.9.0
Requires-Dist: textual>=0.79.1
Requires-Dist: toml>=0.10.2
Requires-Dist: trogon>=0.5.0
